translatium/__init__.py
translatium/config.py
translatium/errors.py
translatium/i18n.py
translatium/utils.py
translatium-0.0.2.dist-info/LICENSE
translatium-0.0.2.dist-info/METADATA
translatium-0.0.2.dist-info/WHEEL
translatium-0.0.2.dist-info/top_level.txt
translatium-0.0.2.dist-info/RECORD
